MANIFEST.in
README.txt
readme.md
setup.py
mongoadmin/__init__.py
mongoadmin/actions.py
mongoadmin/mongohelpers.py
mongoadmin/options.py
mongoadmin/sites.py
mongoadmin/util.py
mongoadmin/validation.py
mongoadmin/views.py
mongoadmin/widgets.py
mongoadmin.egg-info/PKG-INFO
mongoadmin.egg-info/SOURCES.txt
mongoadmin.egg-info/dependency_links.txt
mongoadmin.egg-info/not-zip-safe
mongoadmin.egg-info/requires.txt
mongoadmin.egg-info/top_level.txt
mongoadmin/templates/admin/change_document_list.html
mongoadmin/templatetags/__init__.py
mongoadmin/templatetags/documenttags.py
mongoadmin/templatetags/mongoadmintags.py