Metadata-Version: 1.1
Name: mongoadmin
Version: 0.1.4
Summary: A replacement for django's admin that works with mongodb.
Home-page: http://www.schafproductions.com/projects/mongo-admin/
Author: Jan Schrewe
Author-email: jan@schafproductions.com
License: New BSD License
Platform: UNKNOWN
Classifier: Development Status :: 3 - Alpha
Classifier: Environment :: Web Environment
Classifier: Intended Audience :: Developers
Classifier: License :: OSI Approved :: BSD License
Classifier: Operating System :: OS Independent
Classifier: Programming Language :: Python
Classifier: Framework :: Django
